{
  "mode": "classic",
  "colors": {
    "palette": {
      "textNormal": "#444444",
      "textSecondary": "#A5A5A5",
      "textInverse": "#FFFFFF",
      "iconNormal": "#444444",
      "borderRegularDivider": "#CFCFCF",
      "borderPreviewSelect": "#848484",
      "borderPreviewHover": "#E0E0E0",
      "borderToolbarButtonHover": "#D8DADC",
      "borderToolbar": "#CBCBCB",
      "highlightButtonPressedHover": "#D8DADC",
      "backgroundNormal": "#FFFFFF",
      "backgroundToolbar": "#F1F1F1",
      "backgroundPrimaryDialogButton": "#444444",
      "backgroundPrimaryDialogButtonHover": "#1C1C1C",
      "backgroundScrim": "rgba(0, 0, 0, 0.2)",
      "canvasScrollThumb": "#F1F1F1",
      "canvasScrollThumbHover": "#EBEBEB",
      "scrollThumb": "#E0E0E0",
      "scrollThumbHover": "#F7F7F7",
      "highlightButtonHover": "#EBEBEB",
      "highlightButtonPressed": "#F5F5F5",
      "iconContrastPopover": "#7A7A7A",
      "iconContrastPopoverHover": "#444444"
    },
    "base": {
      "white": "#FFF",
      "black": "#000"
    },
    "other": {
      "gray100": "#AAAAAA",
      "gray200": "#F9F9F9",
      "gray300": "#666666",
      "gray400": "#808080",
      "white100": "#F5F5F5"
    },
    "primary": "#FF6F3D"
  },
  "dropShadows": {
    "shadowMenu": "drop-shadow(0px 2px 5px rgba(0, 0, 0, 0.2))"
  },
  "boxShadows": {
    "shadowWindow": "0px 4px 10px rgba(0, 0, 0, 0.2)",
    "shadowMenu": "0px 2px 5px rgba(0, 0, 0, 0.2)"
  }
}
